synpla_medium/__init__.py
synpla_medium/static/css/medium-formatting.css
synpla_medium/static/css/fonts/fontawesome-webfont.svg
synpla_medium/static/css/fonts/fontawesome-webfont.ttf
synpla_medium/static/css/fonts/fontawesome-webfont.woff
synpla_medium/static/css/fonts/FontAwesome.otf
synpla_medium/static/css/fonts/fontawesome-webfont.eot
synpla_medium/static/css/fonts/fontawesome-webfont.woff2
synpla_medium/static/css/images/resize-bigger.png
synpla_medium/static/css/images/unlink.png
synpla_medium/static/css/images/link.png
synpla_medium/static/css/images/remove.png
synpla_medium/static/css/images/resize-smaller.png
synpla_medium/static/css/libs/font-awesome.min.css
synpla_medium/static/css/libs/medium-editor-insert-plugin-frontend.min.css
synpla_medium/static/css/libs/medium-editor.min.css
synpla_medium/static/css/libs/medium-editor-insert-plugin.min.css
synpla_medium/static/css/libs/medium-themes/bootstrap.min.css
synpla_medium/static/js/app-medium.js
synpla_medium/static/js/libs/jquery.fileupload.js
synpla_medium/static/js/libs/jquery.xdr-transport.js
synpla_medium/static/js/libs/handlebars.runtime.min.js
synpla_medium/static/js/libs/medium-editor-insert-plugin.min.js
synpla_medium/static/js/libs/jquery.xdomainrequest.min.js
synpla_medium/static/js/libs/classlist.min.js
synpla_medium/static/js/libs/jquery-sortable-min.js
synpla_medium/static/js/libs/medium-editor.min.js
synpla_medium/static/js/libs/jquery.ui.widget.js
synpla_medium/static/js/libs/jquery.iframe-transport.js
synpla_medium/templates/medium/macros/medium.html
synpla_medium-0.1.1.dist-info/RECORD
synpla_medium-0.1.1.dist-info/DESCRIPTION.rst
synpla_medium-0.1.1.dist-info/top_level.txt
synpla_medium-0.1.1.dist-info/METADATA
synpla_medium-0.1.1.dist-info/WHEEL
synpla_medium-0.1.1.dist-info/metadata.json
